{
	"home" : { 
		"path" : "app/views/home.php",
		"sessionKey": [{"idUsuario": false}], 
		"sanitize"  : {"requestVars" : true, "code" : true, "sql" : true},
		"errorPath" : "app/views/public_home.php"
	},
	"advertisement/search" : { 
		"path" : "app/controllers/CtrlAdvertisement.php",
		"sessionKey": [{"idUsuario": false}], 
		"sanitize"  : {"requestVars" : true, "code" : true, "sql" : true},
		"errorPath" : "app/views/home.php"
	},
	"advertisement/add" : { 
		"path" : "app/controllers/CtrlAdvertisement.php",
		"sessionKey": [{"idUsuario": false}], 
		"sanitize"  : {"requestVars" : true, "code" : true, "sql" : true},
		"errorPath" : "app/views/home.php"
	},
	"user/add" : { 
		"path" : "app/controllers/CtrlUsers.php",
		"sessionKey": [{"idUsuario": false}], 
		"sanitize"  : {"requestVars" : true, "code" : true, "sql" : true},
		"errorPath" : "app/views/home.php"
	},
	"login" : { 
		"path" : "app/controllers/CtrlUsers.php",
		"sessionKey": [{"idUsuario": false}], 
		"sanitize"  : {"requestVars" : true, "code" : true, "sql" : true},
		"errorPath" : "app/views/home.php"
	}
}
